adafruit_circuitpython_lsm6ds-4.6.1.dist-info/licenses/LICENSE
adafruit_lsm6ds/__init__.py
adafruit_lsm6ds/ism330dhcx.py
adafruit_lsm6ds/lsm6ds3.py
adafruit_lsm6ds/lsm6ds33.py
adafruit_lsm6ds/lsm6ds3trc.py
adafruit_lsm6ds/lsm6dso32.py
adafruit_lsm6ds/lsm6dsox.py
adafruit_circuitpython_lsm6ds-4.6.1.dist-info/METADATA
adafruit_circuitpython_lsm6ds-4.6.1.dist-info/WHEEL
adafruit_circuitpython_lsm6ds-4.6.1.dist-info/top_level.txt
adafruit_circuitpython_lsm6ds-4.6.1.dist-info/RECORD
