Metadata-Version: 2.4
Name: adafruit-circuitpython-lsm6ds
Version: 4.6.1
Summary: CircuitPython helper library for the LSM6DS family of motion sensors from ST
Author-email: Adafruit Industries <circuitpython@adafruit.com>
License: MIT
Project-URL: Homepage, https://github.com/adafruit/Adafruit_CircuitPython_LSM6DS
Keywords: adafruit,blinka,circuitpython,micropython,lsm6ds,lsm6dsox,lsmds33,lsm6dso32,st,imu,gyro,accelerometer,ism330dhcx,imu,gyro,gyroscope,inemo
Classifier: Intended Audience :: Developers
Classifier: Topic :: Software Development :: Libraries
Classifier: Topic :: Software Development :: Embedded Systems
Classifier: Topic :: System :: Hardware
Classifier: License :: OSI Approved :: MIT License
Classifier: Programming Language :: Python :: 3
License-File: LICENSE
Requires-Dist: Adafruit-Blinka
Requires-Dist: adafruit-circuitpython-register
Requires-Dist: adafruit-circuitpython-busdevice
Provides-Extra: optional
Dynamic: license-file
